paystack/__init__.py
paystack/configuration.py
paystack/api/__init__.py
paystack/api/http.py
paystack/api_exceptions/__init__.py
paystack/api_exceptions/authentication_error.py
paystack/api_exceptions/authorization_error.py
paystack/api_exceptions/bank_error.py
paystack/api_exceptions/card_error.py
paystack/api_exceptions/configuration_error.py
paystack/api_exceptions/gateway_timeout_error.py
paystack/api_exceptions/invalid_challenge_error.py
paystack/api_exceptions/invalid_parameter.py
paystack/api_exceptions/invalid_signature_error.py
paystack/api_exceptions/not_found_error.py
paystack/api_exceptions/paystack_error.py
paystack/api_exceptions/request_timeout_error.py
paystack/api_exceptions/server_error.py
paystack/api_exceptions/service_unavailable_error.py
paystack/api_exceptions/test_operation_performed_in_production_error.py
paystack/api_exceptions/too_many_requests_error.py
paystack/api_exceptions/unexpected_error.py
paystack/api_exceptions/upgrade_required_error.py
paystack/api_exceptions/http/__init__.py
paystack/api_exceptions/http/connection_error.py
paystack/api_exceptions/http/invalid_response_error.py
paystack/api_exceptions/http/timeout_error.py
paystack/exceptions/__init__.py
paystack/exceptions/authentication_error.py
paystack/exceptions/authorization_error.py
paystack/exceptions/bank_error.py
paystack/exceptions/card_error.py
paystack/exceptions/configuration_error.py
paystack/exceptions/gateway_timeout_error.py
paystack/exceptions/invalid_challenge_error.py
paystack/exceptions/invalid_parameter.py
paystack/exceptions/invalid_signature_error.py
paystack/exceptions/not_found_error.py
paystack/exceptions/paystack_error.py
paystack/exceptions/request_timeout_error.py
paystack/exceptions/server_error.py
paystack/exceptions/service_unavailable_error.py
paystack/exceptions/test_operation_performed_in_production_error.py
paystack/exceptions/too_many_requests_error.py
paystack/exceptions/unexpected_error.py
paystack/exceptions/upgrade_required_error.py
paystack_api-0.1.2.dist-info/METADATA
paystack_api-0.1.2.dist-info/WHEEL
paystack_api-0.1.2.dist-info/top_level.txt
paystack_api-0.1.2.dist-info/RECORD
