Metadata-Version: 2.1
Name: paystack-api
Version: 0.1.2
Summary: A python app for paystack intergration
Home-page: https://github.com/pypa/sampleproject
Author: Lekan Akanbi
Author-email: lakanbi37@gmail.com
License: UNKNOWN
Platform: UNKNOWN
Classifier: Programming Language :: Python :: 3
Classifier: License :: OSI Approved :: MIT License
Classifier: Operating System :: OS Independent
Requires-Python: >=3.6
